time_series_lib/__init__.py
time_series_lib/anomaly_detection.py
time_series_lib/decomposition.py
time_series_lib/forecasting.py
time_series_lib/modeling.py
time_series_lib/smoothing.py
time_series_lib/spectral_analysis.py
time_series_lib/stationarity.py
time_series_lib/visualization.py
time_series_lib-0.0.1.dist-info/METADATA
time_series_lib-0.0.1.dist-info/WHEEL
time_series_lib-0.0.1.dist-info/top_level.txt
time_series_lib-0.0.1.dist-info/RECORD
