Metadata-Version: 2.1
Name: time-series-lib
Version: 0.0.1
Summary: A time series analysis package for BMSTU AI
Home-page: UNKNOWN
Author: NeuralNine (Florian Dedov)
Author-email: <mail@neuralnine.com>
License: UNKNOWN
Keywords: python,stream,time series
Platform: UNKNOWN
Classifier: Development Status :: 1 - Planning
Classifier: Intended Audience :: Developers
Classifier: Programming Language :: Python :: 3
Classifier: Operating System :: Unix
Classifier: Operating System :: MacOS :: MacOS X
Classifier: Operating System :: Microsoft :: Windows
Requires-Dist: numpy
Requires-Dist: statsmodels
Requires-Dist: keras
Requires-Dist: tensorflow
Requires-Dist: scipy
Requires-Dist: matplotlib
Requires-Dist: pandas
